KeeneticPy/BGPTools.py
KeeneticPy/Keenetic.py
KeeneticPy/__init__.py
KeeneticPy-2.5.dist-info/LICENSE
KeeneticPy-2.5.dist-info/METADATA
KeeneticPy-2.5.dist-info/WHEEL
KeeneticPy-2.5.dist-info/top_level.txt
KeeneticPy-2.5.dist-info/RECORD
