Metadata-Version: 2.1
Name: KeeneticPy
Version: 2.5
Summary: Python Lib for Keenetic Routers
Home-page: https://github.com/keyiflerolsun/KeeneticPy
Author: keyiflerolsun
Author-email: keyiflerolsun@gmail.com
License: GPLv3+
Keywords: KeeneticPy,KekikAkademi,keyiflerolsun
Classifier: Development Status :: 5 - Production/Stable
Classifier: License :: OSI Approved :: GNU General Public License v3 or later (GPLv3+)
Classifier: Programming Language :: Python :: 3
Requires-Python: >=3.10
License-File: LICENSE
Requires-Dist: pip
Requires-Dist: setuptools
Requires-Dist: wheel
Requires-Dist: Kekik
Requires-Dist: httpx
